moskit_cli/__init__.py
moskit_cli/_core.py
moskit_cli/client.py
moskit_cli/enums.py
moskit_cli-0.1.5.dist-info/METADATA
moskit_cli-0.1.5.dist-info/WHEEL
moskit_cli-0.1.5.dist-info/top_level.txt
moskit_cli-0.1.5.dist-info/RECORD
