Metadata-Version: 2.4
Name: moskit-cli
Version: 0.1.5
Summary: Client for MOSKIT controller (Home / Position / Velocity)
Author: Ensume
License-Expression: MIT
Project-URL: Homepage, https://ensume.com
Requires-Python: >=3.8
